cosmian_kms-4.22.1.dist-info/METADATA
cosmian_kms-4.22.1.dist-info/WHEEL
cosmian_kms.libs/libssl-5ca16b9d.so.1.1
cosmian_kms.libs/libcrypto-a9bc086e.so.1.1
cosmian_kms/__init__.py
cosmian_kms/py.typed
cosmian_kms/__init__.pyi
cosmian_kms/cosmian_kms.abi3.so
cosmian_kms-4.22.1.dist-info/RECORD
