Metadata-Version: 2.1
Name: cosmian_kms
Version: 4.22.1
Classifier: Programming Language :: Rust
Classifier: Programming Language :: Python :: Implementation :: CPython
Classifier: Programming Language :: Python :: Implementation :: PyPy
Author: Bruno Grieder <bruno.grieder@cosmian.com>, Emmanuel Coste <emmanuel.coste@cosmian.com>
Author-email: Bruno Grieder <bruno.grieder@cosmian.com>, Emmanuel Coste <emmanuel.coste@cosmian.com>
License: BUSL-1.1
Requires-Python: >=3.7
Project-URL: Source Code, https://github.com/Cosmian/kms
